step_in_line/__init__.py
step_in_line/pipeline.py
step_in_line/step.py
step_in_line/stepfunctions/README.md
step_in_line/stepfunctions/__init__.py
step_in_line/stepfunctions/fields.py
step_in_line/stepfunctions/inputs.py
step_in_line/stepfunctions/steps.py
step_in_line/template_lambda.py
step_in_line/tf.py
step_in_line-0.6.2.dist-info/LICENSE
step_in_line-0.6.2.dist-info/METADATA
step_in_line-0.6.2.dist-info/WHEEL
step_in_line-0.6.2.dist-info/entry_points.txt
step_in_line-0.6.2.dist-info/RECORD
