Metadata-Version: 2.1
Name: step-in-line
Version: 0.6.2
Summary: 
Author: Daniel Stahl
Author-email: danstahl1138@gmail.com
Requires-Python: >=3.9,<4.0
Classifier: Programming Language :: Python :: 3
Classifier: Programming Language :: Python :: 3.9
Classifier: Programming Language :: Python :: 3.10
Classifier: Programming Language :: Python :: 3.11
Classifier: Programming Language :: Python :: 3.12
Provides-Extra: terraform
Requires-Dist: attrs (>=23.2.0,<24.0.0)
Requires-Dist: cdktf (>=0.20.7,<0.21.0) ; extra == "terraform"
Requires-Dist: cdktf-cdktf-provider-aws (>=19.15.0,<20.0.0) ; extra == "terraform"
Requires-Dist: networkx (==3.2.1)
